owui_tools/__init__.py
owui_tools/parameter_confirm.py
owui_tools-0.0.15.dist-info/METADATA
owui_tools-0.0.15.dist-info/WHEEL
owui_tools-0.0.15.dist-info/RECORD
